linkcheck/__init__.py
linkcheck/cli.py
linkcheck/commands.py
linkcheck/django.py
linkcheck/py.typed
linkcheck-0.0.6.dist-info/entry_points.txt
linkcheck-0.0.6.dist-info/LICENSE
linkcheck-0.0.6.dist-info/WHEEL
linkcheck-0.0.6.dist-info/METADATA
linkcheck-0.0.6.dist-info/RECORD
